tiny_3d_engine/__init__.py
tiny_3d_engine/cli.py
tiny_3d_engine/color.py
tiny_3d_engine/engine.py
tiny_3d_engine/geo_loader.py
tiny_3d_engine/part3d.py
tiny_3d_engine/ply_loader.py
tiny_3d_engine/scene3d.py
tiny_3d_engine/screen.py
tiny_3d_engine/viewfield.py
tiny_3d_engine/__pycache__/__init__.cpython-311.pyc
tiny_3d_engine/__pycache__/__init__.cpython-313.pyc
tiny_3d_engine/__pycache__/__init__.cpython-37.pyc
tiny_3d_engine/__pycache__/color.cpython-311.pyc
tiny_3d_engine/__pycache__/color.cpython-313.pyc
tiny_3d_engine/__pycache__/engine.cpython-311.pyc
tiny_3d_engine/__pycache__/engine.cpython-313.pyc
tiny_3d_engine/__pycache__/engine.cpython-37.pyc
tiny_3d_engine/__pycache__/face.cpython-37.pyc
tiny_3d_engine/__pycache__/geo_loader.cpython-311.pyc
tiny_3d_engine/__pycache__/geo_loader.cpython-313.pyc
tiny_3d_engine/__pycache__/part3d.cpython-311.pyc
tiny_3d_engine/__pycache__/part3d.cpython-313.pyc
tiny_3d_engine/__pycache__/part3d.cpython-37.pyc
tiny_3d_engine/__pycache__/ply_loader.cpython-311.pyc
tiny_3d_engine/__pycache__/ply_loader.cpython-313.pyc
tiny_3d_engine/__pycache__/scene3d.cpython-311.pyc
tiny_3d_engine/__pycache__/scene3d.cpython-313.pyc
tiny_3d_engine/__pycache__/scene3d.cpython-37.pyc
tiny_3d_engine/__pycache__/screen.cpython-311.pyc
tiny_3d_engine/__pycache__/screen.cpython-313.pyc
tiny_3d_engine/__pycache__/vertex.cpython-37.pyc
tiny_3d_engine/__pycache__/viewfield.cpython-311.pyc
tiny_3d_engine/__pycache__/viewfield.cpython-313.pyc
tiny_3d_engine/__pycache__/viewfield.cpython-37.pyc
tiny_3d_engine/examples/benchmark.py
tiny_3d_engine/examples/bun_zipper_res2.ply
tiny_3d_engine/examples/bun_zipper_res3.ply
tiny_3d_engine/examples/bun_zipper_res4.geo
tiny_3d_engine/examples/bun_zipper_res4.ply
tiny_3d_engine/examples/cubeExample.py
tiny_3d_engine/examples/dummy.case
tiny_3d_engine/examples/dummy.geo
tiny_3d_engine/examples/geoload.py
tiny_3d_engine/examples/makingparts.py
tiny_3d_engine/examples/rabbit.py
tiny_3d_engine/examples/square.py
tiny_3d_engine-1.0.2.dist-info/licenses/LICENCE.md
tiny_3d_engine-1.0.2.dist-info/METADATA
tiny_3d_engine-1.0.2.dist-info/WHEEL
tiny_3d_engine-1.0.2.dist-info/entry_points.txt
tiny_3d_engine-1.0.2.dist-info/top_level.txt
tiny_3d_engine-1.0.2.dist-info/RECORD
