Metadata-Version: 2.4
Name: tiny_3d_engine
Version: 1.0.2
Summary: Open source tiny 3D engine for tkinter
Author-email: CoopTeam-CERFACS <coop@cerfacs.fr>
License: CeCILL-B FREE SOFTWARE LICENSE AGREEMENT
Project-URL: Homepage, https://gitlab.com/cerfacs/tiny_3d_engine
Project-URL: Documentation, https://tiny-3d-engine.readthedocs.io/en/latest/
Project-URL: Issues, https://gitlab.com/cerfacs/tiny_3d_engine/-/issues
Project-URL: Changelog, https://gitlab.com/cerfacs/tiny_3d_engine/-/blob/master/CHANGELOG.md
Keywords: 3D,python,tkinter
Classifier: Programming Language :: Python :: 3.11
Classifier: Programming Language :: Python :: 3.12
Classifier: Programming Language :: Python :: 3.13
Requires-Python: >=3.11
License-File: LICENCE.md
Requires-Dist: loguru
Requires-Dist: numpy>=2.0
Requires-Dist: click
Requires-Dist: arnica
Requires-Dist: matplotlib
Provides-Extra: docs
Requires-Dist: sphinx_rtd_theme; extra == "docs"
Requires-Dist: recommonmark; extra == "docs"
Provides-Extra: tests
Requires-Dist: pytest; extra == "tests"
Requires-Dist: pytest-coverage; extra == "tests"
Requires-Dist: pytest-allclose; extra == "tests"
Dynamic: license-file
